nanome_url_loader/URLLoader.py
nanome_url_loader/__init__.py
nanome_url_loader-0.1.0.dist-info/LICENSE
nanome_url_loader-0.1.0.dist-info/METADATA
nanome_url_loader-0.1.0.dist-info/WHEEL
nanome_url_loader-0.1.0.dist-info/entry_points.txt
nanome_url_loader-0.1.0.dist-info/top_level.txt
nanome_url_loader-0.1.0.dist-info/RECORD
